README.md
setup.py
django_slappy/__init__.py
django_slappy/apps.py
django_slappy/urls.py
django_slappy/views.py
django_slappy.egg-info/PKG-INFO
django_slappy.egg-info/SOURCES.txt
django_slappy.egg-info/dependency_links.txt
django_slappy.egg-info/requires.txt
django_slappy.egg-info/top_level.txt