Metadata-Version: 2.1
Name: django-slappy
Version: 0.0.2
Summary: Run python in slack
Home-page: https://github.com/Madoshakalaka/django-slappy
Author: Matt Yan
Author-email: syan4@ualberta.ca
License: UNKNOWN
Project-URL: Bug Reports, https://github.com/Madoshakalaka/django-slappy/issues
Project-URL: Say Thanks!, https://github.com/Madoshakalaka/django-slappy
Project-URL: Source, https://github.com/Madoshakalaka/django-slappy
Platform: UNKNOWN
Classifier: Development Status :: 3 - Alpha
Classifier: Intended Audience :: Developers
Classifier: Topic :: Software Development :: Build Tools
Classifier: License :: OSI Approved :: MIT License
Classifier: Programming Language :: Python :: 3.5
Classifier: Programming Language :: Python :: 3.6
Classifier: Programming Language :: Python :: 3.7
Requires-Python: >3.4
